boson/__init__.py
boson/base.py
boson/boson_core_pb2.py
boson/boson_v1_pb2.py
boson/conversion.py
boson/features_pb2.py
boson/pagination.py
boson/grpc/__init__.py
boson/grpc/boson_v1_pb2_grpc.py
boson/grpc/server.py
boson/http/__init__.py
boson/http/server.py
boson_sdk-0.6.12.dist-info/LICENSE
boson_sdk-0.6.12.dist-info/METADATA
boson_sdk-0.6.12.dist-info/WHEEL
boson_sdk-0.6.12.dist-info/top_level.txt
boson_sdk-0.6.12.dist-info/RECORD
