Metadata-Version: 2.1
Name: boson-sdk
Version: 0.6.12
Summary: Python SDK for Boson Geospatial Service Mesh Providers
Author-email: The SeerAI Team <contact@seer.ai>
License: Apache License
Project-URL: Homepage, https://docs.seer.ai/boson
Keywords: geodesic,analysis,seerai,data,science,boson
Classifier: Programming Language :: Python
Classifier: Operating System :: OS Independent
Classifier: Intended Audience :: Developers
Classifier: Intended Audience :: Science/Research
Classifier: Topic :: Scientific/Engineering :: GIS
Classifier: Topic :: Scientific/Engineering :: Visualization
Classifier: Topic :: Scientific/Engineering :: Artificial Intelligence
Classifier: Topic :: Software Development :: Libraries :: Python Modules
Classifier: License :: OSI Approved :: Apache Software License
Requires-Python: >=3.7
License-File: LICENSE
Requires-Dist: geodesic-api >=0.12.0
Requires-Dist: protobuf >=3.20.0
Provides-Extra: all
Requires-Dist: boson-sdk[grpc] ; extra == 'all'
Requires-Dist: boson-sdk[http] ; extra == 'all'
Requires-Dist: boson-sdk[geopandas] ; extra == 'all'
Provides-Extra: dev
Requires-Dist: boson-sdk[all] ; extra == 'dev'
Requires-Dist: pytest ~=6.2.5 ; extra == 'dev'
Requires-Dist: coverage ~=5.5 ; extra == 'dev'
Requires-Dist: flake8 ~=3.9.2 ; extra == 'dev'
Requires-Dist: docker ~=6.0.0 ; extra == 'dev'
Requires-Dist: grpcio-tools ; extra == 'dev'
Provides-Extra: geopandas
Requires-Dist: geopandas >=0.9.0 ; extra == 'geopandas'
Provides-Extra: grpc
Requires-Dist: grpclib >=0.4.2 ; extra == 'grpc'
Requires-Dist: grpcio ~=1.50.0 ; extra == 'grpc'
Provides-Extra: http
Requires-Dist: fastapi[all] ~=0.87.0 ; extra == 'http'
